pyagentx3/__init__.py
pyagentx3/agent.py
pyagentx3/network.py
pyagentx3/pdu.py
pyagentx3/sethandler.py
pyagentx3/tools.py
pyagentx3/updater.py
pyagentx3-0.1.4.dist-info/LICENSE.txt
pyagentx3-0.1.4.dist-info/METADATA
pyagentx3-0.1.4.dist-info/WHEEL
pyagentx3-0.1.4.dist-info/top_level.txt
pyagentx3-0.1.4.dist-info/RECORD
