Metadata-Version: 2.1
Name: pyagentx3
Version: 0.1.4
Summary: AgentX package to extend SNMP with pure Python3.10
Home-page: https://github.com/rprinz08/pyagentx3
Author: Richard Prinz
Author-email: richard.prinz@min.at
License: BSD
Keywords: snmp network agentx
Classifier: Development Status :: 4 - Beta
Classifier: License :: OSI Approved :: BSD License
Classifier: Environment :: No Input/Output (Daemon)
Classifier: Topic :: System :: Monitoring
Classifier: Topic :: System :: Networking
Classifier: Programming Language :: Python
Classifier: Intended Audience :: Developers
Classifier: Intended Audience :: Information Technology
Classifier: Intended Audience :: System Administrators
Classifier: Intended Audience :: Telecommunications Industry
License-File: LICENSE.txt
